{
  "translations": [
    { "english": "hello", "transcription": "[həˈloʊ]", "russian": "привет" },
    { "english": "goodbye", "transcription": "[ˌɡʊdˈbaɪ]", "russian": "до свидания" },
    { "english": "cat", "transcription": "[kæt]", "russian": "кот" },
    { "english": "dog", "transcription": "[dɔɡ]", "russian": "собака" },
    { "english": "apple", "transcription": "[ˈæpəl]", "russian": "яблоко" },
    { "english": "ice-cream", "transcription": "[ˈaɪsˌkrim]", "russian": "мороженое" },
    { "english": "bread", "transcription": "[brɛd]", "russian": "хлеб" },
    { "english": "chair", "transcription": "[tʃɛr]", "russian": "стул" },
    { "english": "table", "transcription": "[ˈteɪbəl]", "russian": "стол" },
    { "english": "house", "transcription": "[haʊs]", "russian": "дом" },
    { "english": "car", "transcription": "[kɑr]", "russian": "машина" },
    { "english": "book", "transcription": "[bʊk]", "russian": "книга" },
    { "english": "pen", "transcription": "[pɛn]", "russian": "ручка" },
    { "english": "pencil", "transcription": "[ˈpɛnsəl]", "russian": "карандаш" },
    { "english": "phone", "transcription": "[foʊn]", "russian": "телефон" },
    { "english": "computer", "transcription": "[kəmˈpjuːtər]", "russian": "компьютер" },
    { "english": "door", "transcription": "[dɔr]", "russian": "дверь" },
    { "english": "window", "transcription": "[ˈwɪndoʊ]", "russian": "окно" },
    { "english": "tree", "transcription": "[tri]", "russian": "дерево" },
    { "english": "flower", "transcription": "[ˈflaʊər]", "russian": "цветок" },
    { "english": "bird", "transcription": "[bɜrd]", "russian": "птица" },
    { "english": "fish", "transcription": "[fɪʃ]", "russian": "рыба" },
    { "english": "butterfly", "transcription": "[ˈbʌtərflaɪ]", "russian": "бабочка" },
    { "english": "sun", "transcription": "[sʌn]", "russian": "солнце" },
    { "english": "moon", "transcription": "[muːn]", "russian": "луна" },
    { "english": "star", "transcription": "[stɑːr]", "russian": "звезда" },
    { "english": "cloud", "transcription": "[klaʊd]", "russian": "облако" },
    { "english": "rain", "transcription": "[reɪn]", "russian": "дождь" },
    { "english": "snow", "transcription": "[snoʊ]", "russian": "снег" },
    { "english": "wind", "transcription": "[wɪnd]", "russian": "ветер" },
    { "english": "fire", "transcription": "[ˈfaɪər]", "russian": "огонь" },
    { "english": "earth", "transcription": "[ɜːrθ]", "russian": "земля" },
    { "english": "mountain", "transcription": "[ˈmaʊntən]", "russian": "гора" },
    { "english": "river", "transcription": "[ˈrɪvər]", "russian": "река" },
    { "english": "sea", "transcription": "[si]", "russian": "море" },
    { "english": "lake", "transcription": "[leɪk]", "russian": "озеро" },
    { "english": "forest", "transcription": "[ˈfɔːrɪst]", "russian": "лес" },
    { "english": "road", "transcription": "[roʊd]", "russian": "дорога" },
    { "english": "city", "transcription": "[ˈsɪti]", "russian": "город" },
    { "english": "country", "transcription": "[ˈkʌntri]", "russian": "страна" },
    { "english": "world", "transcription": "[wɜːrld]", "russian": "мир" },
    {"english": "horse", "transcription": "[hɔrs]", "russian": "лошадь"},
{"english": "cow", "transcription": "[kaʊ]", "russian": "корова"},
{"english": "sheep", "transcription": "[ʃiːp]", "russian": "овца"},
{"english": "pig", "transcription": "[pɪɡ]", "russian": "свинья"},
{"english": "chicken", "transcription": "[ˈtʃɪkɪn]", "russian": "курица"},
{"english": "duck", "transcription": "[dʌk]", "russian": "утка"},
{"english": "goose", "transcription": "[ɡuːs]", "russian": "гусь"},
{"english": "turkey", "transcription": "[ˈtɜrki]", "russian": "индейка"},
{"english": "frog", "transcription": "[frɔɡ]", "russian": "лягушка"},
{"english": "snake", "transcription": "[sneɪk]", "russian": "змея"},
{ "english": "apple", "transcription": "[ˈæpəl]", "russian": "яблоко" },
{ "english": "banana", "transcription": "[bəˈnænə]", "russian": "банан" },
{ "english": "orange", "transcription": "[ˈɔrɪndʒ]", "russian": "апельсин" },
{ "english": "strawberry", "transcription": "[ˈstrɔːbəri]", "russian": "клубника" },
{ "english": "grape", "transcription": "[ɡreɪp]", "russian": "виноград" },
{ "english": "watermelon", "transcription": "[ˈwɔːtərmelən]", "russian": "арбуз" },
{ "english": "pineapple", "transcription": "[ˈpaɪnæpl]", "russian": "ананас" },
{ "english": "kiwi", "transcription": "[ˈkiːwiː]", "russian": "киви" },
{ "english": "cherry", "transcription": "[ˈtʃer.i]", "russian": "вишня" },
{ "english": "pear", "transcription": "[per]", "russian": "груша" }


  ]
}


